example0934/__init__.py
example0934/example.py
example0934-0.2.0.dist-info/METADATA
example0934-0.2.0.dist-info/WHEEL
example0934-0.2.0.dist-info/top_level.txt
example0934-0.2.0.dist-info/RECORD
