Metadata-Version: 2.1
Name: example0934
Version: 0.2.0
Summary: A example Python package
Home-page: https://github.com/cobrobrown/dslab/pip_package/example0934
Author: Conner Brown
Author-email: cobrobrown@gmail.com
License: BSD 2-clause
Platform: UNKNOWN
Classifier: Development Status :: 1 - Planning
Classifier: Intended Audience :: Science/Research
Classifier: License :: OSI Approved :: BSD License
Classifier: Operating System :: POSIX :: Linux
Classifier: Programming Language :: Python :: 3.8
